edtf/__init__.py
edtf/appsettings.py
edtf/convert.py
edtf/fields.py
edtf/jdutil.py
edtf/tests.py
edtf/natlang/__init__.py
edtf/natlang/en.py
edtf/natlang/tests.py
edtf/parser/__init__.py
edtf/parser/edtf_exceptions.py
edtf/parser/grammar.py
edtf/parser/parser_classes.py
edtf/parser/tests.py
edtf-5.0.0.dist-info/LICENSE
edtf-5.0.0.dist-info/METADATA
edtf-5.0.0.dist-info/WHEEL
edtf-5.0.0.dist-info/top_level.txt
edtf-5.0.0.dist-info/RECORD
