Metadata-Version: 2.1
Name: edtf
Version: 5.0.0
Summary: Python implementation of Library of Congress EDTF (Extended Date Time Format) specification
Author: Alastair Weakley, Greg Turner, James Murty, Mark Finger, Sabine Müller, Cole Crawford, Klaus Rettinghaus
Author-email: The Interaction Consortium <studio@interaction.net.au>
Maintainer-email: The Interaction Consortium <studio@interaction.net.au>
Project-URL: homepage, https://github.com/ixc/python-edtf
Project-URL: issues, https://github.com/ixc/python-edtf/issues
Project-URL: repository, https://github.com/ixc/python-edtf.git
Project-URL: changelog, https://github.com/ixc/python-edtf/blob/main/changelog.rst
Classifier: Intended Audience :: Developers
Classifier: Intended Audience :: End Users/Desktop
Classifier: License :: OSI Approved :: MIT License
Classifier: Operating System :: MacOS :: MacOS X
Classifier: Operating System :: POSIX :: Linux
Classifier: Programming Language :: Python :: 3
Classifier: Programming Language :: Python :: 3.8
Classifier: Programming Language :: Python :: 3.9
Classifier: Programming Language :: Python :: 3.10
Classifier: Programming Language :: Python :: 3.11
Classifier: Programming Language :: Python :: 3.12
Requires-Python: >=3.8
License-File: LICENSE
Requires-Dist: python-dateutil
Requires-Dist: pyparsing
Provides-Extra: test
Requires-Dist: django <5.0,>=4.2 ; extra == 'test'
Requires-Dist: pytest ; extra == 'test'
Requires-Dist: pytest-django ; extra == 'test'
Requires-Dist: pytest-benchmark ; extra == 'test'
Requires-Dist: ruff ; extra == 'test'
Requires-Dist: pre-commit ; extra == 'test'
Requires-Dist: coverage ; extra == 'test'
Requires-Dist: pytest-cov ; extra == 'test'
Requires-Dist: junitparser ; extra == 'test'
